pytest_bdd/__init__.py
pytest_bdd/allure_logging.py
pytest_bdd/collector.py
pytest_bdd/const.py
pytest_bdd/cucumber_json.py
pytest_bdd/exceptions.py
pytest_bdd/generation.py
pytest_bdd/gherkin_terminal_reporter.py
pytest_bdd/hook.py
pytest_bdd/hooks.py
pytest_bdd/markdown_parser.js
pytest_bdd/message_plugin.py
pytest_bdd/mimetypes.py
pytest_bdd/npm_resource.py
pytest_bdd/packaging.py
pytest_bdd/parser.py
pytest_bdd/parsers.py
pytest_bdd/plugin.py
pytest_bdd/reporting.py
pytest_bdd/runner.py
pytest_bdd/scenario.py
pytest_bdd/scenario_locator.py
pytest_bdd/steps.py
pytest_bdd/tag_expression.py
pytest_bdd/testing_utils.py
pytest_bdd/utils.py
pytest_bdd/warning_types.py
pytest_bdd/webloc.py
pytest_bdd/compatibility/__init__.py
pytest_bdd/compatibility/allure.py
pytest_bdd/compatibility/parser.py
pytest_bdd/compatibility/path.py
pytest_bdd/compatibility/pytest.py
pytest_bdd/compatibility/struct_bdd.py
pytest_bdd/compatibility/tomllib.py
pytest_bdd/compatibility/typing.py
pytest_bdd/compatibility/importlib/__init__.py
pytest_bdd/compatibility/importlib/metadata.py
pytest_bdd/compatibility/importlib/resources.py
pytest_bdd/model/__init__.py
pytest_bdd/model/gherkin_document.py
pytest_bdd/model/messages_extension.py
pytest_bdd/script/__init__.py
pytest_bdd/script/bdd_tree_to_rst.py
pytest_bdd/struct_bdd/__init__.py
pytest_bdd/struct_bdd/model.py
pytest_bdd/struct_bdd/model_builder.py
pytest_bdd/struct_bdd/parser.py
pytest_bdd/struct_bdd/plugin.py
pytest_bdd/template/__init__.py
pytest_bdd/template/test.py.mak
pytest_bdd_ng-2.3.1.dist-info/AUTHORS.rst
pytest_bdd_ng-2.3.1.dist-info/LICENSE.rst
pytest_bdd_ng-2.3.1.dist-info/METADATA
pytest_bdd_ng-2.3.1.dist-info/WHEEL
pytest_bdd_ng-2.3.1.dist-info/entry_points.txt
pytest_bdd_ng-2.3.1.dist-info/top_level.txt
pytest_bdd_ng-2.3.1.dist-info/RECORD
