Metadata-Version: 2.1
Name: pytest-bdd-ng
Version: 2.3.1
Summary: BDD for pytest
Author-email: Oleg Pidsadnyi <oleg.pidsadnyi@gmail.com>, Anatoly Bubenkov <bubenkoff@gmail.com>, Adam Coddington <me@adamcoddington.net>, Albert-Jan Nijburg <albertjan@curit.com>, Alessio Bogon <youtux@gmail.com>, Andrey Makhnach <andrey.makhnach@gmail.com>, Aron Curzon <curzona@gmail.com>, Dmitrijs Milajevs <dimazest@gmail.com>, Dmitry Kolyagin <pauk-slon@users.noreply.github.com>, Florian Bruhin <me@the-compiler.org>, Floris Bruynooghe <flub@devork.be>, Harro van der Klauw <hvdklauw@gmail.com>
Maintainer-email: Konstantin Goloveshko <kostya.goloveshko@gmail.com>
License: .. toctree::
Project-URL: Documentation, https://pytest-bdd-ng.readthedocs.io/en/default/
Project-URL: Repository, https://github.com/elchupanebrej/pytest-bdd-ng
Classifier: Development Status :: 4 - Beta
Classifier: Framework :: Pytest
Classifier: Intended Audience :: Developers
Classifier: License :: OSI Approved :: MIT License
Classifier: Operating System :: POSIX
Classifier: Operating System :: Microsoft :: Windows
Classifier: Operating System :: MacOS :: MacOS X
Classifier: Topic :: Software Development :: Testing
Classifier: Topic :: Software Development :: Libraries
Classifier: Topic :: Utilities
Classifier: Programming Language :: Python :: 3
Classifier: Programming Language :: Python :: 3.9
Classifier: Programming Language :: Python :: 3.10
Classifier: Programming Language :: Python :: 3.11
Classifier: Programming Language :: Python :: 3.12
Classifier: Programming Language :: Python :: 3.13
Requires-Python: >=3.9
License-File: LICENSE.rst
License-File: AUTHORS.rst
Requires-Dist: aiohttp
Requires-Dist: attrs
Requires-Dist: certifi
Requires-Dist: chevron
Requires-Dist: ci-environment
Requires-Dist: cuke-messages==0.1.0
Requires-Dist: cucumber-expressions
Requires-Dist: decopatch
Requires-Dist: docopt-ng
Requires-Dist: filelock
Requires-Dist: gherkin-official<30,>=24
Requires-Dist: importlib-metadata; python_version < "3.10.0"
Requires-Dist: importlib-resources
Requires-Dist: makefun
Requires-Dist: Mako
Requires-Dist: ordered_set
Requires-Dist: packaging
Requires-Dist: parse
Requires-Dist: parse_type>=0.6.0
Requires-Dist: pathvalidate
Requires-Dist: py
Requires-Dist: pydantic>=2.0.3
Requires-Dist: pytest>=5.2
Requires-Dist: cucumber-tag-expressions
Requires-Dist: typing-extensions; python_version < "3.11.0"
Provides-Extra: allure
Requires-Dist: allure-python-commons; extra == "allure"
Requires-Dist: allure-pytest; extra == "allure"
Provides-Extra: doc-gen
Requires-Dist: docopt-ng; extra == "doc-gen"
Requires-Dist: pandoc; extra == "doc-gen"
Requires-Dist: panflute; extra == "doc-gen"
Requires-Dist: pycmarkgfm; extra == "doc-gen"
Requires-Dist: pypandoc; extra == "doc-gen"
Provides-Extra: full
Requires-Dist: pytest-bdd-ng[allure]; extra == "full"
Requires-Dist: pytest-bdd-ng[doc-gen]; extra == "full"
Requires-Dist: pytest-bdd-ng[struct-bdd]; extra == "full"
Requires-Dist: pytest-bdd-ng[test]; extra == "full"
Requires-Dist: pytest-bdd-ng[testtypes]; extra == "full"
Provides-Extra: struct-bdd
Requires-Dist: hjson; extra == "struct-bdd"
Requires-Dist: json5; extra == "struct-bdd"
Requires-Dist: pyhocon; extra == "struct-bdd"
Requires-Dist: tomli; python_version < "3.11.0" and extra == "struct-bdd"
Requires-Dist: PyYAML; extra == "struct-bdd"
Requires-Dist: types-PyYAML; extra == "struct-bdd"
Provides-Extra: test
Requires-Dist: allure-python-commons-test; extra == "test"
Requires-Dist: execnet; extra == "test"
Requires-Dist: packaging; extra == "test"
Requires-Dist: PyHamcrest; extra == "test"
Requires-Dist: pytest-httpserver; extra == "test"
Requires-Dist: python-coveralls; extra == "test"
Requires-Dist: pytest-bdd-ng[doc-gen]; python_version >= "3.12.0" and extra == "test"
Provides-Extra: testenv
Requires-Dist: tox~=4.0; extra == "testenv"
Requires-Dist: codecov; extra == "testenv"
Provides-Extra: testtypes
Requires-Dist: mypy; extra == "testtypes"
Requires-Dist: types-certifi; extra == "testtypes"
Requires-Dist: types-docopt; extra == "testtypes"
Requires-Dist: types-setuptools; extra == "testtypes"
